qrstyler/__init__.py
qrstyler/generator.py
qrstyler/themes.py
qrstyler/icons/facebook_logo.png
qrstyler/icons/github_logo.png
qrstyler/icons/instagram_logo.png
qrstyler/icons/linkedin_logo.png
qrstyler/icons/linktree_logo.png
qrstyler/icons/whatsapp_logo.png
qrstyler/icons/x_logo.png
qrstyler/icons/youtube_logo.png
qrstyler-1.1.2.dist-info/licenses/LICENSE.md
qrstyler-1.1.2.dist-info/METADATA
qrstyler-1.1.2.dist-info/WHEEL
qrstyler-1.1.2.dist-info/top_level.txt
qrstyler-1.1.2.dist-info/RECORD
