Metadata-Version: 2.4
Name: qrstyler
Version: 1.1.2
Summary: A simple QR code generator
Home-page: https://github.com/vipulm124/qrgenerator
Author: Vipul Malhotra
Author-email: vipulm124@gmail.com
Classifier: Programming Language :: Python :: 3
Classifier: License :: OSI Approved :: MIT License
Classifier: Operating System :: OS Independent
Requires-Python: >=3.6
License-File: LICENSE.md
Requires-Dist: qrcode>=7.0
Requires-Dist: Pillow>=8.0
Dynamic: author
Dynamic: author-email
Dynamic: classifier
Dynamic: description
Dynamic: description-content-type
Dynamic: home-page
Dynamic: license-file
Dynamic: requires-dist
Dynamic: requires-python
Dynamic: summary
